streamlit_chromadb_connection/__init__.py
streamlit_chromadb_connection/chromadb_connection.py
streamlit_chromadb_connection-1.0.5.dist-info/LICENSE
streamlit_chromadb_connection-1.0.5.dist-info/METADATA
streamlit_chromadb_connection-1.0.5.dist-info/WHEEL
streamlit_chromadb_connection-1.0.5.dist-info/top_level.txt
streamlit_chromadb_connection-1.0.5.dist-info/RECORD
