Metadata-Version: 2.1
Name: streamlit_chromadb_connection
Version: 1.0.5
Summary: A simple adapter connection for any Streamlit LLM-powered app to use ChromaDB vector database.
Author-email: Dev317 <mineskiroxro@gmail.com>
Project-URL: Homepage, https://github.com/Dev317/streamlit_chromadb_connection
Project-URL: Issues, https://github.com/Dev317/streamlit_chromadb_connection/issues
Classifier: Programming Language :: Python :: 3
Classifier: License :: OSI Approved :: MIT License
Classifier: Operating System :: OS Independent
Requires-Python: >=3.8
License-File: LICENSE
Requires-Dist: altair ==5.3.0
Requires-Dist: annotated-types ==0.7.0
Requires-Dist: anyio ==4.4.0
Requires-Dist: asgiref ==3.8.1
Requires-Dist: attrs ==23.2.0
Requires-Dist: backoff ==2.2.1
Requires-Dist: bcrypt ==4.1.3
Requires-Dist: blinker ==1.8.2
Requires-Dist: build ==1.2.1
Requires-Dist: cachetools ==5.3.3
Requires-Dist: certifi ==2024.7.4
Requires-Dist: charset-normalizer ==3.3.2
Requires-Dist: chroma-hnswlib ==0.7.3
Requires-Dist: chromadb ==0.5.3
Requires-Dist: click ==8.1.7
Requires-Dist: coloredlogs ==15.0.1
Requires-Dist: Deprecated ==1.2.14
Requires-Dist: dnspython ==2.6.1
Requires-Dist: email-validator ==2.2.0
Requires-Dist: fastapi ==0.111.0
Requires-Dist: fastapi-cli ==0.0.4
Requires-Dist: filelock ==3.15.4
Requires-Dist: flatbuffers ==24.3.25
Requires-Dist: fsspec ==2024.6.1
Requires-Dist: gitdb ==4.0.11
Requires-Dist: GitPython ==3.1.43
Requires-Dist: google-auth ==2.32.0
Requires-Dist: googleapis-common-protos ==1.63.2
Requires-Dist: grpcio ==1.64.1
Requires-Dist: h11 ==0.14.0
Requires-Dist: httpcore ==1.0.5
Requires-Dist: httptools ==0.6.1
Requires-Dist: httpx ==0.27.0
Requires-Dist: huggingface-hub ==0.23.4
Requires-Dist: humanfriendly ==10.0
Requires-Dist: idna ==3.7
Requires-Dist: importlib-metadata ==7.1.0
Requires-Dist: importlib-resources ==6.4.0
Requires-Dist: Jinja2 ==3.1.4
Requires-Dist: jsonschema ==4.23.0
Requires-Dist: jsonschema-specifications ==2023.12.1
Requires-Dist: kubernetes ==30.1.0
Requires-Dist: markdown-it-py ==3.0.0
Requires-Dist: MarkupSafe ==2.1.5
Requires-Dist: mdurl ==0.1.2
Requires-Dist: mmh3 ==4.1.0
Requires-Dist: monotonic ==1.6
Requires-Dist: mpmath ==1.3.0
Requires-Dist: numpy ==1.26.4
Requires-Dist: oauthlib ==3.2.2
Requires-Dist: onnxruntime ==1.18.1
Requires-Dist: opentelemetry-api ==1.25.0
Requires-Dist: opentelemetry-exporter-otlp-proto-common ==1.25.0
Requires-Dist: opentelemetry-exporter-otlp-proto-grpc ==1.25.0
Requires-Dist: opentelemetry-instrumentation ==0.46b0
Requires-Dist: opentelemetry-instrumentation-asgi ==0.46b0
Requires-Dist: opentelemetry-instrumentation-fastapi ==0.46b0
Requires-Dist: opentelemetry-proto ==1.25.0
Requires-Dist: opentelemetry-sdk ==1.25.0
Requires-Dist: opentelemetry-semantic-conventions ==0.46b0
Requires-Dist: opentelemetry-util-http ==0.46b0
Requires-Dist: orjson ==3.10.6
Requires-Dist: overrides ==7.7.0
Requires-Dist: packaging ==24.1
Requires-Dist: pandas ==2.2.2
Requires-Dist: pillow ==10.4.0
Requires-Dist: posthog ==3.5.0
Requires-Dist: protobuf ==4.25.3
Requires-Dist: pyarrow ==16.1.0
Requires-Dist: pyasn1 ==0.6.0
Requires-Dist: pyasn1-modules ==0.4.0
Requires-Dist: pydantic ==2.8.2
Requires-Dist: pydantic-core ==2.20.1
Requires-Dist: pydeck ==0.9.1
Requires-Dist: Pygments ==2.18.0
Requires-Dist: PyPika ==0.48.9
Requires-Dist: pyproject-hooks ==1.1.0
Requires-Dist: python-dateutil ==2.9.0.post0
Requires-Dist: python-dotenv ==1.0.1
Requires-Dist: python-multipart ==0.0.9
Requires-Dist: pytz ==2024.1
Requires-Dist: PyYAML ==6.0.1
Requires-Dist: referencing ==0.35.1
Requires-Dist: requests ==2.32.3
Requires-Dist: requests-oauthlib ==2.0.0
Requires-Dist: rich ==13.7.1
Requires-Dist: rpds-py ==0.19.0
Requires-Dist: rsa ==4.9
Requires-Dist: setuptools ==70.3.0
Requires-Dist: shellingham ==1.5.4
Requires-Dist: six ==1.16.0
Requires-Dist: smmap ==5.0.1
Requires-Dist: sniffio ==1.3.1
Requires-Dist: starlette ==0.37.2
Requires-Dist: streamlit ==1.36.0
Requires-Dist: sympy ==1.13.0
Requires-Dist: tenacity ==8.5.0
Requires-Dist: tokenizers ==0.19.1
Requires-Dist: toml ==0.10.2
Requires-Dist: toolz ==0.12.1
Requires-Dist: tornado ==6.4.1
Requires-Dist: tqdm ==4.66.4
Requires-Dist: typer ==0.12.3
Requires-Dist: typing-extensions ==4.12.2
Requires-Dist: tzdata ==2024.1
Requires-Dist: ujson ==5.10.0
Requires-Dist: urllib3 ==2.2.2
Requires-Dist: uvicorn ==0.30.1
Requires-Dist: uvloop ==0.19.0
Requires-Dist: watchfiles ==0.22.0
Requires-Dist: websocket-client ==1.8.0
Requires-Dist: websockets ==12.0
Requires-Dist: wrapt ==1.16.0
Requires-Dist: zipp ==3.19.2
